pywix/__init__.py
pywix/_version.py
pywix/wix_download.py
pywix/files/LuxTasks.dll
pywix/files/Microsoft.Deployment.Compression.Cab.dll
pywix/files/Microsoft.Deployment.Compression.dll
pywix/files/Microsoft.Deployment.Resources.dll
pywix/files/Microsoft.Deployment.WindowsInstaller.Package.dll
pywix/files/Microsoft.Deployment.WindowsInstaller.dll
pywix/files/ThmViewer.exe
pywix/files/WixBalExtension.dll
pywix/files/WixComPlusExtension.dll
pywix/files/WixCop.exe
pywix/files/WixDependencyExtension.dll
pywix/files/WixDifxAppExtension.dll
pywix/files/WixDirectXExtension.dll
pywix/files/WixFirewallExtension.dll
pywix/files/WixGamingExtension.dll
pywix/files/WixHttpExtension.dll
pywix/files/WixIIsExtension.dll
pywix/files/WixLuxExtension.dll
pywix/files/WixMsmqExtension.dll
pywix/files/WixNetFxExtension.dll
pywix/files/WixPSExtension.dll
pywix/files/WixSqlExtension.dll
pywix/files/WixTagExtension.dll
pywix/files/WixTasks.dll
pywix/files/WixUIExtension.dll
pywix/files/WixUtilExtension.dll
pywix/files/WixVSExtension.MSBuild12.dll
pywix/files/WixVSExtension.MSBuild14.dll
pywix/files/WixVSExtension.dll
pywix/files/candle.exe
pywix/files/candle.exe.config
pywix/files/darice.cub
pywix/files/dark.exe
pywix/files/dark.exe.config
pywix/files/difxapp_x64.wixlib
pywix/files/difxapp_x86.wixlib
pywix/files/heat.exe
pywix/files/heat.exe.config
pywix/files/insignia.exe
pywix/files/insignia.exe.config
pywix/files/light.exe
pywix/files/light.exe.config
pywix/files/lit.exe
pywix/files/lit.exe.config
pywix/files/lux.exe
pywix/files/lux.exe.config
pywix/files/lux.targets
pywix/files/melt.exe
pywix/files/melt.exe.config
pywix/files/mergemod.cub
pywix/files/mergemod.dll
pywix/files/mspatchc.dll
pywix/files/nit.exe
pywix/files/nit.exe.config
pywix/files/pyro.exe
pywix/files/pyro.exe.config
pywix/files/retina.exe
pywix/files/retina.exe.config
pywix/files/shine.exe
pywix/files/shine.exe.config
pywix/files/smoke.exe
pywix-0.1.6.dist-info/DESCRIPTION.rst
pywix-0.1.6.dist-info/METADATA
pywix-0.1.6.dist-info/RECORD
pywix-0.1.6.dist-info/WHEEL
pywix-0.1.6.dist-info/metadata.json
pywix-0.1.6.dist-info/top_level.txt
